python_caltrain/__init__.py
python_caltrain/__version__.py
python_caltrain/caltrain.py
python_caltrain/data/caltrain_gtfs_latest.zip
python_caltrain-2019.4.1.dist-info/LICENSE
python_caltrain-2019.4.1.dist-info/METADATA
python_caltrain-2019.4.1.dist-info/WHEEL
python_caltrain-2019.4.1.dist-info/top_level.txt
python_caltrain-2019.4.1.dist-info/zip-safe
python_caltrain-2019.4.1.dist-info/RECORD
