Metadata-Version: 2.1
Name: python-caltrain
Version: 2019.4.1
Summary: A library for working with raw Caltrain scheduling data in Python
Home-page: https://github.com/ownaginatious/python-caltrain
Author: Dillon Dixon
Author-email: dillondixon@gmail.com
License: MIT
Keywords: caltrain,python
Platform: UNKNOWN
Classifier: License :: OSI Approved :: MIT License
Classifier: Programming Language :: Python :: 3.4
Classifier: Programming Language :: Python :: 3.5
Classifier: Programming Language :: Python :: 3.6
Classifier: Programming Language :: Python :: 3.7
